ragex/__init__.py
ragex/community/__init__.py
ragex/community/config.py
ragex/community/constants.py
ragex/community/initialise.py
ragex/community/jwt.py
ragex/community/local.py
ragex/community/metrics.py
ragex/community/scheduler.py
ragex/community/server.py
ragex/community/sql_migrations.py
ragex/community/tracker_utils.py
ragex/community/utils.py
ragex/community/version.py
ragex/community/api/__init__.py
ragex/community/api/app.py
ragex/community/api/decorators.py
ragex/community/api/blueprints/__init__.py
ragex/community/api/blueprints/git.py
ragex/community/api/blueprints/images.py
ragex/community/api/blueprints/intents.py
ragex/community/api/blueprints/interface.py
ragex/community/api/blueprints/models.py
ragex/community/api/blueprints/nlg.py
ragex/community/api/blueprints/nlu.py
ragex/community/api/blueprints/project.py
ragex/community/api/blueprints/response.py
ragex/community/api/blueprints/stack.py
ragex/community/api/blueprints/telemetry.py
ragex/community/database/__init__.py
ragex/community/database/admin.py
ragex/community/database/analytics.py
ragex/community/database/base.py
ragex/community/database/conversation.py
ragex/community/database/data.py
ragex/community/database/domain.py
ragex/community/database/intent.py
ragex/community/database/model.py
ragex/community/database/response.py
ragex/community/database/service.py
ragex/community/database/utils.py
ragex/community/database/schema_migrations/__init__.py
ragex/community/database/schema_migrations/alembic.ini
ragex/community/database/schema_migrations/alembic/README
ragex/community/database/schema_migrations/alembic/__init__.py
ragex/community/database/schema_migrations/alembic/env.py
ragex/community/database/schema_migrations/alembic/script.py.mako
ragex/community/database/schema_migrations/alembic/utils.py
ragex/community/database/schema_migrations/alembic/versions/__init__.py
ragex/community/database/schema_migrations/alembic/versions/migration_2019_06_03_initial_migration_2a216ed121dd.py
rage_ts-0.4.18.dist-info/METADATA
rage_ts-0.4.18.dist-info/WHEEL
rage_ts-0.4.18.dist-info/top_level.txt
rage_ts-0.4.18.dist-info/RECORD
