Metadata-Version: 2.1
Name: rage-ts
Version: 0.4.18
Summary: rage-ts
Home-page: https://gitlab.com/rageoflove/rage-ts
Author: rage
Author-email: rageoflove@gmail.com
License: UNKNOWN
Download-URL: https://gitlab.com/rageoflove/rage-ts/archive/0.0.tar.gz
Keywords: rage-ts
Platform: UNKNOWN
Classifier: Programming Language :: Python :: 3
Classifier: Programming Language :: Python :: 3.2
Classifier: Programming Language :: Python :: 3.3
Classifier: Programming Language :: Python :: 3.4
Classifier: Programming Language :: Python :: 3.5
Classifier: Programming Language :: Python :: 3.6
Classifier: Programming Language :: Python :: 3.7
Requires-Python: >=3
